filedialogs/__init__.py
filedialogs/__main__.py
filedialogs/linux_kdialog.py
filedialogs/linux_zenity.py
filedialogs/mac.py
filedialogs/tkinter.py
filedialogs/windows.py
filedialogs-0.4.2.dist-info/licenses/LICENSE
filedialogs-0.4.2.dist-info/METADATA
filedialogs-0.4.2.dist-info/WHEEL
filedialogs-0.4.2.dist-info/entry_points.txt
filedialogs-0.4.2.dist-info/top_level.txt
filedialogs-0.4.2.dist-info/RECORD
