Metadata-Version: 2.4
Name: filedialogs
Version: 0.4.2
Summary: Platform independent interface for file dialogs
Author-email: "Adrian F. Hoefflin" <srccircumflex@outlook.com>
License: MIT License
Project-URL: Repository, https://github.com/srccircumflex/filedialogs
Classifier: Development Status :: 7 - Inactive
Classifier: Intended Audience :: Developers
Classifier: Operating System :: OS Independent
Classifier: Topic :: Desktop Environment :: File Managers
Requires-Python: >=3.10
License-File: LICENSE
Requires-Dist: pywin32; platform_system == "Windows"
Dynamic: license-file
